iterfuncs/__init__.py
iterfuncs/asyncio.py
iterfuncs/cache.py
iterfuncs/itertools.py
iterfuncs/typing.py
iterfuncs-1.0.1.dist-info/licenses/LICENSE
iterfuncs-1.0.1.dist-info/METADATA
iterfuncs-1.0.1.dist-info/WHEEL
iterfuncs-1.0.1.dist-info/top_level.txt
iterfuncs-1.0.1.dist-info/RECORD
