Metadata-Version: 2.4
Name: iterfuncs
Version: 1.0.1
Summary: Collection of iteration, caching and async tools
Home-page: https://github.com/Quartz-Vision/python-iterfuncs
Author: liava
Author-email: liava@tuta.io
Classifier: Programming Language :: Python :: 3.13
Classifier: Operating System :: OS Independent
Requires-Python: >=3.13
License-File: LICENSE
Dynamic: author
Dynamic: author-email
Dynamic: classifier
Dynamic: description
Dynamic: description-content-type
Dynamic: home-page
Dynamic: license-file
Dynamic: requires-python
Dynamic: summary
